ovds_utils/__init__.py
ovds_utils/exceptions.py
ovds_utils/logging.py
ovds_utils/metadata.py
ovds_utils/vds.py
ovds_utils/ovds/__init__.py
ovds_utils/ovds/copy.py
ovds_utils/ovds/enums.py
ovds_utils/ovds/utils.py
ovds_utils/ovds/writing.py
ovds_utils-0.3.1.dist-info/LICENSE
ovds_utils-0.3.1.dist-info/METADATA
ovds_utils-0.3.1.dist-info/WHEEL
ovds_utils-0.3.1.dist-info/top_level.txt
ovds_utils-0.3.1.dist-info/RECORD
