Metadata-Version: 2.1
Name: ovds-utils
Version: 0.3.1
Summary: Utilities package for Open VDS.
Home-page: https://github.com/micmurawski/ovds-utils/
Author: Michal Murawski
Author-email: mmurawski777@gmail.com
License: MIT
Platform: UNKNOWN
Classifier: License :: OSI Approved :: MIT License
Classifier: Programming Language :: Python :: 3
Classifier: Programming Language :: Python :: 3.6
Classifier: Programming Language :: Python :: 3.7
Classifier: Programming Language :: Python :: 3.8
Requires-Python: >=3.7,<4.0
License-File: LICENSE
Requires-Dist: humanfriendly (>=10.0)
Requires-Dist: openvds (<4.0.0,>=2.2.0)
Requires-Dist: tqdm (~=4.64.0)
